taurex_fastchem/.DS_Store
taurex_fastchem/__init__.py
taurex_fastchem/data/logK.dat
taurex_fastchem/data/logK_extended.dat
taurex_fastchem/data/logK_wo_ions.dat
taurex_fastchem/py.typed
taurex_fastchem/types.py
taurex_fastchem/util.py
taurex_fastchem-1.1.0.dist-info/LICENSE
taurex_fastchem-1.1.0.dist-info/METADATA
taurex_fastchem-1.1.0.dist-info/WHEEL
taurex_fastchem-1.1.0.dist-info/entry_points.txt
taurex_fastchem-1.1.0.dist-info/RECORD
