Metadata-Version: 2.3
Name: taurex-fastchem
Version: 1.1.0
Summary: TauRex FastChem
Home-page: https://github.com/ahmed-f-alrefaie/taurex-fastchem
License: MIT
Author: Ahmed F. Al-Refaie
Author-email: ahmed.al-refaie.12@ucl.ac.uk
Requires-Python: >=3.9,<3.13
Classifier: Development Status :: 1 - Planning
Classifier: License :: OSI Approved :: MIT License
Classifier: Programming Language :: Python :: 3
Classifier: Programming Language :: Python :: 3.9
Classifier: Programming Language :: Python :: 3.10
Classifier: Programming Language :: Python :: 3.11
Classifier: Programming Language :: Python :: 3.12
Requires-Dist: numpy (<2.0.0)
Requires-Dist: pyfastchem (>=3.1.2,<4.0.0)
Requires-Dist: taurex (>=3.1.14,<4.0.0)
Project-URL: Changelog, https://github.com/ahmed-f-alrefaie/taurex-fastchem/releases
Project-URL: Documentation, https://taurex-fastchem.readthedocs.io
Project-URL: Repository, https://github.com/ahmed-f-alrefaie/taurex-fastchem
